natera_uploader-1.0.0.dist-info/DESCRIPTION.rst
natera_uploader-1.0.0.dist-info/LICENSE.txt
natera_uploader-1.0.0.dist-info/METADATA
natera_uploader-1.0.0.dist-info/RECORD
natera_uploader-1.0.0.dist-info/WHEEL
natera_uploader-1.0.0.dist-info/entry_points.txt
natera_uploader-1.0.0.dist-info/metadata.json
natera_uploader-1.0.0.dist-info/top_level.txt
soyuz/__init__.py
soyuz/configuration.py
soyuz/data.py
soyuz/dx.py
soyuz/entrypoint.py
soyuz/utils.py
