Metadata-Version: 2.0
Name: natera-uploader
Version: 1.0.0
Summary: Natera Uploader
Home-page: UNKNOWN
Author: Nikita Berezin
Author-email: nberezin@natera.com
License: UNKNOWN
Platform: UNKNOWN
Classifier: Programming Language :: Python :: 2.7
Requires-Dist: dxpy
